py_ullr/__init__.py
py_ullr/client.py
py_ullr/exceptions.py
py_ullr/auth/__init__.py
py_ullr/auth/authenticator.py
py_ullr/models/__init__.py
py_ullr/rest/__init__.py
py_ullr/rest/applications.py
py_ullr/rest/base.py
py_ullr/rest/content.py
py_ullr/rest/records.py
py_ullr/rest/reports.py
py_ullr/rest/search.py
py_ullr/rest/users.py
py_ullr/rest/value_lists.py
py_ullr/webservices/__init__.py
py_ullr/webservices/client.py
py_ullr-1.0.1.dist-info/licenses/LICENSE
py_ullr-1.0.1.dist-info/METADATA
py_ullr-1.0.1.dist-info/WHEEL
py_ullr-1.0.1.dist-info/top_level.txt
py_ullr-1.0.1.dist-info/RECORD
